[{"pseudo":"anis","password":"anis"},{"pseudo":"papier","password":"papier"},{"pseudo":"Sheet","password":"Sheet","adverse":""},{"pseudo":"Captain","password":"Captain"},{"pseudo":"float","password":"float"},{"pseudo":"admin","password":"admin"},{"pseudo":"k","password":"q"},{"pseudo":"Gomme","password":"Gomme"},{"pseudo":"Kaby","password":"1"},{"pseudo":"le big m","password":"cmoi"},{"pseudo":"ptibonome","password":"HMMM64-69"},{"pseudo":"bernice","password":"1710"},{"pseudo":"Remember","password":"1234"}]